{
	"name": "e_Level4",
	"events": [
		{
			"eventType": "include",
			"includeSheet": "e_Global"
		},
		{
			"eventType": "group",
			"disabled": false,
			"title": "LAYOUT_LEVEL4",
			"description": "",
			"isActiveOnStart": true,
			"children": [
				{
					"eventType": "block",
					"conditions": [
						{
							"id": "on-start-of-layout",
							"objectClass": "System",
							"sid": 841716292189454
						}
					],
					"actions": [
						{
							"id": "set-eventvar-value",
							"objectClass": "System",
							"sid": 825337471470670,
							"parameters": {
								"variable": "cursor",
								"value": "\"default\""
							}
						},
						{
							"id": "set-boolean-eventvar",
							"objectClass": "System",
							"sid": 150091552612062,
							"parameters": {
								"variable": "PlayerMoving",
								"value": "false"
							}
						},
						{
							"id": "set-eventvar-value",
							"objectClass": "System",
							"sid": 141248360089053,
							"parameters": {
								"variable": "layout",
								"value": "\"Level4\""
							}
						}
					],
					"sid": 800703476232868
				}
			],
			"sid": 105721928691137
		}
	],
	"sid": 282853676340560
}